{
  "date" : "Thu, 14 Nov, 2024 09:50:14 +0000",
  "doco" : "For each file: start is seconds after start activity occurred. Length = milliseconds activity took",
  "files" : [
    {
      "name" : "/fsh-generated/resources/ImplementationGuide-ans.fhir.fr.tddui.json",
      "size" : 9276,
      "processes" : [
        {
          "activity" : "load",
          "start" : 29,
          "length" : 28
        },
        {
          "activity" : "checkR4R4B",
          "start" : 29,
          "length" : 5
        },
        {
          "activity" : "generateNarratives",
          "start" : 29,
          "length" : 178
        },
        {
          "activity" : "validate",
          "start" : 31,
          "length" : 562
        },
        {
          "activity" : "scanForUsageStats",
          "start" : 32,
          "length" : 1
        },
        {
          "activity" : "generate1",
          "start" : 32,
          "length" : 121
        },
        {
          "activity" : "generate2",
          "start" : 37,
          "length" : 89
        },
        {
          "activity" : "generateValidationPack",
          "start" : 50,
          "length" : 3
        },
        {
          "activity" : "scanExamplesForR5",
          "start" : 57,
          "length" : 2
        }
      ]
    },
    {
      "name" : "fsh-generated/resources/Bundle-TDDUIBundleExample.json",
      "size" : 3306,
      "processes" : [
        {
          "activity" : "loadResources",
          "start" : 28,
          "length" : 23
        },
        {
          "activity" : "load",
          "start" : 29,
          "length" : 18
        },
        {
          "activity" : "generateNarratives",
          "start" : 29,
          "length" : 174
        },
        {
          "activity" : "validate",
          "start" : 32,
          "length" : 332
        },
        {
          "activity" : "generate1",
          "start" : 32,
          "length" : 30
        },
        {
          "activity" : "generate2",
          "start" : 37,
          "length" : 19
        },
        {
          "activity" : "scanExamplesForR5",
          "start" : 57,
          "length" : 1
        }
      ]
    },
    {
      "name" : "fsh-generated/resources/CapabilityStatement-TDDUIConsommateur.json",
      "size" : 1866,
      "processes" : [
        {
          "activity" : "loadResources",
          "start" : 28,
          "length" : 16
        },
        {
          "activity" : "load",
          "start" : 29,
          "length" : 25
        },
        {
          "activity" : "generateNarratives",
          "start" : 29,
          "length" : 53
        },
        {
          "activity" : "validate",
          "start" : 31,
          "length" : 234
        },
        {
          "activity" : "generate1",
          "start" : 32,
          "length" : 36
        },
        {
          "activity" : "generate2",
          "start" : 37,
          "length" : 42
        },
        {
          "activity" : "generateValidationPack",
          "start" : 50,
          "length" : 1
        }
      ]
    },
    {
      "name" : "fsh-generated/resources/CapabilityStatement-TDDUIProducteur.json",
      "size" : 1797,
      "processes" : [
        {
          "activity" : "loadResources",
          "start" : 28,
          "length" : 11
        },
        {
          "activity" : "load",
          "start" : 29,
          "length" : 16
        },
        {
          "activity" : "checkR4R4B",
          "start" : 29,
          "length" : 1
        },
        {
          "activity" : "generateNarratives",
          "start" : 30,
          "length" : 23
        },
        {
          "activity" : "validate",
          "start" : 31,
          "length" : 9
        },
        {
          "activity" : "generate1",
          "start" : 33,
          "length" : 35
        },
        {
          "activity" : "generate2",
          "start" : 37,
          "length" : 15
        },
        {
          "activity" : "generateValidationPack",
          "start" : 50,
          "length" : 1
        }
      ]
    },
    {
      "name" : "fsh-generated/resources/DocumentReference-TDDUIDocumentReferenceExample.json",
      "size" : 952,
      "processes" : [
        {
          "activity" : "loadResources",
          "start" : 28,
          "length" : 11
        },
        {
          "activity" : "generateNarratives",
          "start" : 30,
          "length" : 48
        },
        {
          "activity" : "validate",
          "start" : 32,
          "length" : 6
        },
        {
          "activity" : "generate1",
          "start" : 33,
          "length" : 15
        },
        {
          "activity" : "generate2",
          "start" : 37,
          "length" : 9
        }
      ]
    },
    {
      "name" : "fsh-generated/resources/StructureDefinition-tddui-bundle.json",
      "size" : 2074,
      "processes" : [
        {
          "activity" : "loadResources",
          "start" : 28,
          "length" : 12
        },
        {
          "activity" : "load-configure",
          "start" : 29,
          "length" : 1
        },
        {
          "activity" : "load",
          "start" : 29,
          "length" : 19
        },
        {
          "activity" : "generateSnapshots",
          "start" : 29,
          "length" : 110
        },
        {
          "activity" : "generateNarratives",
          "start" : 30,
          "length" : 68
        },
        {
          "activity" : "validate",
          "start" : 30,
          "length" : 1010
        },
        {
          "activity" : "scanForUsageStats",
          "start" : 32,
          "length" : 1
        },
        {
          "activity" : "generate1",
          "start" : 33,
          "length" : 367
        },
        {
          "activity" : "generate2",
          "start" : 37,
          "length" : 1998
        },
        {
          "activity" : "generateValidationPack",
          "start" : 50,
          "length" : 18
        },
        {
          "activity" : "scanExamplesForR5",
          "start" : 57,
          "length" : 2
        }
      ]
    },
    {
      "name" : "fsh-generated/resources/StructureDefinition-tddui-documentreference.json",
      "size" : 14607,
      "processes" : [
        {
          "activity" : "loadResources",
          "start" : 28,
          "length" : 15
        },
        {
          "activity" : "load",
          "start" : 29,
          "length" : 27
        },
        {
          "activity" : "generateSnapshots",
          "start" : 29,
          "length" : 59
        },
        {
          "activity" : "generateNarratives",
          "start" : 30,
          "length" : 57
        },
        {
          "activity" : "validate",
          "start" : 31,
          "length" : 362
        },
        {
          "activity" : "scanForUsageStats",
          "start" : 32,
          "length" : 1
        },
        {
          "activity" : "generate1",
          "start" : 33,
          "length" : 497
        },
        {
          "activity" : "generate2",
          "start" : 39,
          "length" : 1286
        },
        {
          "activity" : "generateValidationPack",
          "start" : 50,
          "length" : 13
        },
        {
          "activity" : "scanExamplesForR5",
          "start" : 57,
          "length" : 2
        }
      ]
    }
  ]
}
